molify/__init__.py
molify/ase2x.py
molify/bond_order.py
molify/com.py
molify/compress.py
molify/networkx2x.py
molify/pack.py
molify/rdkit2x.py
molify/smiles2x.py
molify/substructure.py
molify/utils.py
molify-0.0.1a1.dist-info/METADATA
molify-0.0.1a1.dist-info/WHEEL
molify-0.0.1a1.dist-info/licenses/LICENSE
molify-0.0.1a1.dist-info/RECORD
