Metadata-Version: 2.4
Name: molify
Version: 0.0.1a1
Summary: Interface between rdkit and ASE
Author-email: Fabian Zills <fzills@icp.uni-stuttgart.de>
License-Expression: Apache-2.0
License-File: LICENSE
Requires-Python: >=3.10
Requires-Dist: ase>=3.25.0
Requires-Dist: matplotlib>=3.10.1
Requires-Dist: networkx>=3.4.2
Requires-Dist: rdkit>=2024
Provides-Extra: vesin
Requires-Dist: vesin>=0.3.7; extra == 'vesin'
